Metadata-Version: 1.0
Name: ProjectGlass
Version: 0.1
Summary: Imports the data
Home-page: https://github.com/prabhat003/ProjectGlass.git
Author: Prabhat Kumar Prabhakar
Author-email: prabhatp@winjit.com
License: Winjit Technologies Pvt. Ltd
Platform: UNKNOWN
